googleads_housekeeper/__init__.py
googleads_housekeeper/bootstrap.py
googleads_housekeeper/views.py
googleads_housekeeper/adapters/__init__.py
googleads_housekeeper/adapters/legacy_adapter.py
googleads_housekeeper/adapters/notifications.py
googleads_housekeeper/adapters/orm.py
googleads_housekeeper/adapters/publisher.py
googleads_housekeeper/adapters/repository.py
googleads_housekeeper/domain/__init__.py
googleads_housekeeper/domain/commands.py
googleads_housekeeper/domain/events.py
googleads_housekeeper/domain/core/__init__.py
googleads_housekeeper/domain/core/entity.py
googleads_housekeeper/domain/core/exclusion_specification.py
googleads_housekeeper/domain/core/execution.py
googleads_housekeeper/domain/core/rules_parser.py
googleads_housekeeper/domain/core/settings.py
googleads_housekeeper/domain/core/task.py
googleads_housekeeper/domain/external_parsers/__init__.py
googleads_housekeeper/domain/external_parsers/base_parser.py
googleads_housekeeper/domain/external_parsers/external_entity_parser.py
googleads_housekeeper/domain/external_parsers/parsers.py
googleads_housekeeper/domain/external_parsers/website_parser.py
googleads_housekeeper/domain/placement_handler/__init__.py
googleads_housekeeper/domain/placement_handler/entities.py
googleads_housekeeper/domain/placement_handler/placement_excluder.py
googleads_housekeeper/domain/placement_handler/placement_fetcher.py
googleads_housekeeper/domain/placement_handler/placement_service.py
googleads_housekeeper/services/__init__.py
googleads_housekeeper/services/enums.py
googleads_housekeeper/services/handlers.py
googleads_housekeeper/services/messagebus.py
googleads_housekeeper/services/unit_of_work.py
googleads_housekeeper-0.3.12.dist-info/METADATA
googleads_housekeeper-0.3.12.dist-info/WHEEL
googleads_housekeeper-0.3.12.dist-info/top_level.txt
googleads_housekeeper-0.3.12.dist-info/RECORD
