Metadata-Version: 2.4
Name: googleads-housekeeper
Version: 0.3.12
Summary: description
Author-email: "Google Inc. (gTech gPS CSE team)" <no-reply@google.com>
License: Apache 2.0
Classifier: Development Status :: 4 - Beta
Classifier: Programming Language :: Python
Requires-Python: >=3.9
Requires-Dist: google-ads-api-report-fetcher[pandas]
Requires-Dist: SQLAlchemy==1.4.46
Requires-Dist: beautifulsoup4
Requires-Dist: google-api-python-client
Requires-Dist: psycopg2-binary
Requires-Dist: croniter
Requires-Dist: aiohttp
Requires-Dist: slack_sdk
Requires-Dist: garf_core
Requires-Dist: garf-youtube-data-api
Requires-Dist: legacy-cgi
Requires-Dist: pyyaml
Provides-Extra: gcp
Requires-Dist: google-cloud-firestore; extra == "gcp"
Requires-Dist: google-cloud-pubsub; extra == "gcp"
Requires-Dist: appengine-python-standard>=1.0.0; extra == "gcp"
Provides-Extra: all
Requires-Dist: googleads_housekeeper[gcp]; extra == "all"
